makefilepy/Command.py
makefilepy/Makefile.py
makefilepy/Variable.py
makefilepy/__init__.py
tests/__init__.py
tests/test_Command.py
tests/test_Makefile.py
tests/test_Variable.py
makefilepy-0.0.2.dist-info/METADATA
makefilepy-0.0.2.dist-info/WHEEL
makefilepy-0.0.2.dist-info/top_level.txt
makefilepy-0.0.2.dist-info/RECORD
