Metadata-Version: 2.1
Name: makefilepy
Version: 0.0.2
Summary: Create Makefile files dynamically
Home-page: https://github.com/alvarofpp/makefilepy
Author: Álvaro Ferreira Pires de Paiva
Author-email: alvarofepipa@gmail.com
License: UNKNOWN
Platform: UNKNOWN
Classifier: Programming Language :: Python :: 3
Classifier: License :: OSI Approved :: MIT License
Classifier: Operating System :: OS Independent
Requires-Dist: pydantic (>=1.10.0)
